setup.py
storage_utils/__init__.py
storage_utils/__version__.py
storage_utils/base.py
storage_utils/hdfs.py
storage_utils/local.py
storage_utils/s3.py
storage_utils.egg-info/PKG-INFO
storage_utils.egg-info/SOURCES.txt
storage_utils.egg-info/dependency_links.txt
storage_utils.egg-info/requires.txt
storage_utils.egg-info/top_level.txt